friendlysam/compat.py
friendlysam/models.py
friendlysam/opt.py
friendlysam/parts.py
friendlysam/util.py
friendlysam/__init__.py
friendlysam/solvers/pulpengine.py
friendlysam/solvers/__init__.py
friendlysam-0.3.0.dist-info/DESCRIPTION.rst
friendlysam-0.3.0.dist-info/METADATA
friendlysam-0.3.0.dist-info/metadata.json
friendlysam-0.3.0.dist-info/RECORD
friendlysam-0.3.0.dist-info/top_level.txt
friendlysam-0.3.0.dist-info/WHEEL
