Metadata-Version: 2.0
Name: friendlysam
Version: 0.3.0
Summary: Toolbox for optimization-based modelling and simulation.
Home-page: http://friendly-sam.readthedocs.org
Author: Rasmus Einarsson
Author-email: rasmus.einarsson@sp.se
License: LGPLv3
Platform: UNKNOWN
Classifier: Development Status :: 3 - Alpha
Classifier: Intended Audience :: Developers
Classifier: Intended Audience :: Science/Research
Classifier: Topic :: Scientific/Engineering
Classifier: License :: OSI Approved :: GNU Lesser General Public License v3 (LGPLv3)
Classifier: Programming Language :: Python :: 3
Classifier: Programming Language :: Python :: 3.4
Requires-Dist: PuLP (==1.5.8)
Requires-Dist: networkx (==1.9.1)
Provides-Extra: pandas
Requires-Dist: pandas (>=0.16.1); extra == 'pandas'
Provides-Extra: pickling
Requires-Dist: dill (>=0.2.2); extra == 'pickling'
